client/__init__.py
client/api_client.py
client/configuration.py
client/rest.py
client/api/__init__.py
client/api/auth_api.py
client/api/health_api.py
client/api/orders_api.py
client/api/products_api.py
client/api/shops_api.py
client/api/supplier_api.py
client/models/__init__.py
client/models/active_order_list_response.py
client/models/alternative_products.py
client/models/api_response_active_order.py
client/models/api_response_authentication_response.py
client/models/api_response_get_shop_response.py
client/models/api_response_list_cancel_option_response.py
client/models/api_response_list_order_response.py
client/models/api_response_object.py
client/models/api_response_order_report_response.py
client/models/api_response_order_report_response_wrapper.py
client/models/api_response_pageable_response_shop_products_response.py
client/models/api_response_pageable_response_shop_products_response_data.py
client/models/api_response_price_and_quantity_batch_response.py
client/models/api_response_product_batch_ticket_response.py
client/models/api_response_shop_couriers_working_status_response.py
client/models/api_response_shop_working_hours_response.py
client/models/api_response_void.py
client/models/artisan_order_response.py
client/models/authentication_response.py
client/models/bag_response.py
client/models/cancel_option_response.py
client/models/cancel_order_request.py
client/models/chain_shop_response.py
client/models/customer_response.py
client/models/field_validation.py
client/models/filter_line_order_response.py
client/models/filter_order_response.py
client/models/general_error.py
client/models/general_error_wrapper.py
client/models/get_shop_response.py
client/models/health_response.py
client/models/internal_error.py
client/models/internal_error_wrapper.py
client/models/invoice_address_response.py
client/models/invoice_request.py
client/models/menu_options_response.py
client/models/model5001_internal_error.py
client/models/name_response.py
getir_locals_client-1.0.0.dist-info/METADATA
getir_locals_client-1.0.0.dist-info/WHEEL
getir_locals_client-1.0.0.dist-info/top_level.txt
getir_locals_client-1.0.0.dist-info/RECORD
